README
setup.py
django_mesh/__init__.py
django_mesh/admin.py
django_mesh/managers.py
django_mesh/models.py
django_mesh/urls.py
django_mesh/views.py
django_mesh.egg-info/PKG-INFO
django_mesh.egg-info/SOURCES.txt
django_mesh.egg-info/dependency_links.txt
django_mesh.egg-info/requires.txt
django_mesh.egg-info/top_level.txt
django_mesh/tests/__init__.py
django_mesh/tests/test_managers.py
django_mesh/tests/test_models.py
django_mesh/tests/test_urls.py
django_mesh/tests/util.py