Metadata-Version: 1.0
Name: django-mesh
Version: 0.1.0
Summary: A Django blog.
Home-page: https://github.com/SeanHayes/django-mesh
Author: Seán Hayes
Author-email: sean@seanhayes.name
License: GPL
Keywords: django blog
Platform: UNKNOWN
Classifier: Development Status :: 3 - Alpha
Classifier: Framework :: Django
Classifier: Intended Audience :: Developers
Classifier: License :: OSI Approved :: GNU General Public License (GPL)
Classifier: Operating System :: OS Independent
Classifier: Programming Language :: Python
Classifier: Programming Language :: Python :: 2.6
Classifier: Topic :: Internet :: WWW/HTTP :: Dynamic Content
Classifier: Topic :: Internet :: WWW/HTTP :: Site Management
Classifier: Topic :: Software Development :: Libraries
Classifier: Topic :: Software Development :: Libraries :: Python Modules
